{
  "id": "INTJ-ISTP",
  "surface": "INTJ",
  "deep": "ISTP",
  "title": "ケンタウロス宿せし軍師",
  "codes": "INTJ - ISTP",
  "catch": "頭で戦略を練る人の奥に、手を動かして確かめたい職人が息づいている。",
  "lead": [
    "外に見せるのは、抽象的な戦略を頭の中で組み立てる思考型の顔。だが内側では、実際に手を動かして確かめたいケンタウロスの本能が静かに疼いている。",
    "理屈の人に見えて、実は体で覚えた感覚を誰より信頼している。"
  ],
  "dynamics": [
    "軍師は頭の中で最適解を組み立てる。ケンタウロスは実際にやってみて確かめる。この二つは順番が逆になりがちで、頭で完璧に詰めてから動きたい表層と、まず試したい深層がせめぎ合う。",
    "議論より実践で納得するタイプであるにもかかわらず、それを表に出さず頭の中だけで処理しようとするため、机上の空論に自分自身が一番苛立つことがある。"
  ],
  "strength": "緻密な戦略と、実際に手を動かして検証する力を両方持つ。理論倒れにならない現実的な強さがある。",
  "shadow": "頭で考えすぎて動き出しが遅れ、本当は早く試したかった内なる衝動を無視し続けてしまう。",
  "stress": "限界を超えると、思考を放棄していきなり無言で動き出し、周囲を置き去りにする。",
  "tale": [
    "城の外れに、誰も知らない鍛冶場があった。城主は時折そこに一人で立ち寄り、剣の重さを黙って確かめていた。",
    "――その静かな鍛冶場が、あなたの中の軍師にもある。"
  ],
  "share": "頭で考える戦略家の奥に、手で確かめたい職人が隠れている。",
  "gauges_example": {
    "I": { "winner": "本物I", "pct": 73, "note": "一人で手を動かす作業の時間が、頭の疲れを取り除いてくれる。" },
    "N": { "winner": "排除型N", "pct": 55, "note": "抽象的な戦略を、実際に試せる具体的な手順へすぐに変換できる。" },
    "T": { "winner": "排除型T", "pct": 68, "note": "感覚的な納得より、論理と実証の両方が揃って初めて安心できる。" },
    "J": { "winner": "隠れP", "pct": 58, "note": "計画を立てたい気持ちの裏で、実は手探りで進めたい衝動も強く残っている。" }
  },
  "paid_toc": [
    "天職と、活きる職場環境／枯れる職場環境",
    "消耗しやすい働き方と、キャリアの決断の罠",
    "恋愛での仮面と本音 ─ どう口説き、どう愛されたいか",
    "惹かれやすい相手、離れられなくなる相手",
    "パートナーに読んでほしいページ",
    "幻獣相性図 ─ 十六幻獣との縁"
  ]
}
